HumbleBench/__init__.py
HumbleBench/models/__init__.py
HumbleBench/models/base.py
HumbleBench/utils/__init__.py
HumbleBench/utils/constant.py
HumbleBench/utils/entity.py
HumbleBench/utils/io.py
HumbleBench/utils/logger.py
HumbleBench/utils/metrics.py
HumbleBench/utils/rand.py
humblebench-1.0.2.dist-info/METADATA
humblebench-1.0.2.dist-info/WHEEL
humblebench-1.0.2.dist-info/top_level.txt
humblebench-1.0.2.dist-info/RECORD
