Metadata-Version: 2.4
Name: HumbleBench
Version: 1.0.2
Summary: A comprehensive benchmark for hallucinations in multimodal large language models.
Author-email: Bingkui Tong <bingkuitong@gmail.com>
License-Expression: MIT
Requires-Python: >=3.9.0
Requires-Dist: tqdm
Requires-Dist: pydantic>=2.11.7
Requires-Dist: requests
Requires-Dist: datasets==3.6.0
Requires-Dist: pillow==11.2.1
Requires-Dist: rich==14.0.0
Requires-Dist: numpy==1.26.3
